{
    "AP_selection": {
        "1": 1,
        "2": 1,
        "3": 1,
        "4": 1,
        "5": 7,
        "6": 7,
        "7": 6,
        "8": 8,
        "9": 9,
        "10": 9,
        "11": 8,
        "12": 7,
        "13": 17,
        "14": 17,
        "15": 17,
        "16": 27,
        "17": 27,
        "18": 26,
        "19": 27,
        "20": 26,
        "21": 26,
        "22": 26,
        "23": 25,
        "24": 34
    },
    "1": {
        "nf0": "edge_server_server_0",
        "nf1": "robot_sq1_fogNode_2",
        "nf2": "edge_server_server_0",
        "nf3": "robot_sq1_fogNode_2",
        "nf4": "edge_server_server_0",
        "nf5": "edge_server_server_0",
        "nf6": "robot_sq1_fogNode_2",
        "nf7": "edge_server_server_0",
        "nf8": "edge_server_server_0",
        "nf9": "edge_server_server_0",
        "nf10": "robot_sq1_fogNode_8",
        "nf11": "edge_server_server_0",
        "nf12": "edge_server_server_0",
        "nf13": "robot_sq1_fogNode_3",
        "nf14": "edge_server_server_0",
        "nf15": "edge_server_server_0",
        "nf16": "edge_server_server_0",
        "nf17": "edge_server_server_0",
        "nf18": "edge_server_server_0",
        "nf19": "robot_sq1_fogNode_2",
        "nf20": "edge_server_server_0",
        "nf21": "edge_server_server_0",
        "nf22": "edge_server_server_0",
        "nf23": "edge_server_server_0",
        "nf24": "edge_server_server_0",
        "nf25": "robot_sq1_fogNode_3",
        "worked": true,
        "Objective_value": 95.19021,
        "Running_time": 0.2686126232147217
    },
    "2": {
        "nf0": "edge_server_server_0",
        "nf1": "robot_sq1_fogNode_2",
        "nf2": "edge_server_server_0",
        "nf3": "robot_sq1_fogNode_2",
        "nf4": "edge_server_server_0",
        "nf5": "edge_server_server_0",
        "nf6": "robot_sq1_fogNode_2",
        "nf7": "edge_server_server_0",
        "nf8": "edge_server_server_0",
        "nf9": "edge_server_server_0",
        "nf10": "robot_sq1_fogNode_8",
        "nf11": "edge_server_server_0",
        "nf12": "edge_server_server_0",
        "nf13": "robot_sq1_fogNode_3",
        "nf14": "edge_server_server_0",
        "nf15": "edge_server_server_0",
        "nf16": "edge_server_server_0",
        "nf17": "edge_server_server_0",
        "nf18": "edge_server_server_0",
        "nf19": "robot_sq1_fogNode_2",
        "nf20": "edge_server_server_0",
        "nf21": "edge_server_server_0",
        "nf22": "edge_server_server_0",
        "nf23": "edge_server_server_0",
        "nf24": "edge_server_server_0",
        "nf25": "robot_sq1_fogNode_3",
        "worked": true,
        "Objective_value": 95.19021,
        "Running_time": 0.2155599594116211
    },
    "3": {
        "nf0": "edge_server_server_0",
        "nf1": "robot_sq1_fogNode_2",
        "nf2": "edge_server_server_0",
        "nf3": "robot_sq1_fogNode_2",
        "nf4": "edge_server_server_0",
        "nf5": "edge_server_server_0",
        "nf6": "robot_sq1_fogNode_2",
        "nf7": "edge_server_server_0",
        "nf8": "edge_server_server_0",
        "nf9": "edge_server_server_0",
        "nf10": "robot_sq1_fogNode_8",
        "nf11": "edge_server_server_0",
        "nf12": "edge_server_server_0",
        "nf13": "robot_sq1_fogNode_3",
        "nf14": "edge_server_server_0",
        "nf15": "edge_server_server_0",
        "nf16": "edge_server_server_0",
        "nf17": "edge_server_server_0",
        "nf18": "edge_server_server_0",
        "nf19": "robot_sq1_fogNode_2",
        "nf20": "edge_server_server_0",
        "nf21": "edge_server_server_0",
        "nf22": "edge_server_server_0",
        "nf23": "edge_server_server_0",
        "nf24": "edge_server_server_0",
        "nf25": "robot_sq1_fogNode_3",
        "worked": true,
        "Objective_value": 95.19021,
        "Running_time": 0.21590852737426758
    },
    "4": {
        "nf0": "edge_server_server_0",
        "nf1": "robot_sq1_fogNode_2",
        "nf2": "edge_server_server_0",
        "nf3": "robot_sq1_fogNode_2",
        "nf4": "edge_server_server_0",
        "nf5": "edge_server_server_0",
        "nf6": "robot_sq1_fogNode_2",
        "nf7": "edge_server_server_0",
        "nf8": "edge_server_server_0",
        "nf9": "edge_server_server_0",
        "nf10": "robot_sq1_fogNode_8",
        "nf11": "edge_server_server_0",
        "nf12": "edge_server_server_0",
        "nf13": "robot_sq1_fogNode_3",
        "nf14": "edge_server_server_0",
        "nf15": "edge_server_server_0",
        "nf16": "edge_server_server_0",
        "nf17": "edge_server_server_0",
        "nf18": "edge_server_server_0",
        "nf19": "robot_sq1_fogNode_2",
        "nf20": "edge_server_server_0",
        "nf21": "edge_server_server_0",
        "nf22": "edge_server_server_0",
        "nf23": "edge_server_server_0",
        "nf24": "edge_server_server_0",
        "nf25": "robot_sq1_fogNode_3",
        "worked": true,
        "Objective_value": 95.19021,
        "Running_time": 0.2158806324005127
    },
    "5": {
        "nf0": "edge_server_server_0",
        "nf1": "robot_sq1_fogNode_2",
        "nf2": "edge_server_server_0",
        "nf3": "robot_sq1_fogNode_2",
        "nf4": "edge_server_server_0",
        "nf5": "edge_server_server_0",
        "nf6": "robot_sq1_fogNode_2",
        "nf7": "edge_server_server_0",
        "nf8": "edge_server_server_0",
        "nf9": "edge_server_server_0",
        "nf10": "robot_sq1_fogNode_3",
        "nf11": "edge_server_server_0",
        "nf12": "edge_server_server_0",
        "nf13": "robot_sq1_fogNode_3",
        "nf14": "edge_server_server_0",
        "nf15": "edge_server_server_0",
        "nf16": "edge_server_server_0",
        "nf17": "edge_server_server_0",
        "nf18": "edge_server_server_0",
        "nf19": "robot_sq1_fogNode_2",
        "nf20": "edge_server_server_0",
        "nf21": "edge_server_server_0",
        "nf22": "edge_server_server_0",
        "nf23": "edge_server_server_0",
        "nf24": "edge_server_server_0",
        "nf25": "robot_sq1_fogNode_3",
        "worked": true,
        "Objective_value": 95.19021,
        "Running_time": 0.2762181758880615
    },
    "6": {
        "nf0": "edge_server_server_0",
        "nf1": "robot_sq1_fogNode_2",
        "nf2": "edge_server_server_0",
        "nf3": "robot_sq1_fogNode_2",
        "nf4": "edge_server_server_0",
        "nf5": "edge_server_server_0",
        "nf6": "robot_sq1_fogNode_2",
        "nf7": "edge_server_server_0",
        "nf8": "edge_server_server_0",
        "nf9": "edge_server_server_0",
        "nf10": "robot_sq1_fogNode_3",
        "nf11": "edge_server_server_0",
        "nf12": "edge_server_server_0",
        "nf13": "robot_sq1_fogNode_3",
        "nf14": "edge_server_server_0",
        "nf15": "edge_server_server_0",
        "nf16": "edge_server_server_0",
        "nf17": "edge_server_server_0",
        "nf18": "edge_server_server_0",
        "nf19": "robot_sq1_fogNode_2",
        "nf20": "edge_server_server_0",
        "nf21": "edge_server_server_0",
        "nf22": "edge_server_server_0",
        "nf23": "edge_server_server_0",
        "nf24": "edge_server_server_0",
        "nf25": "robot_sq1_fogNode_3",
        "worked": true,
        "Objective_value": 95.19021,
        "Running_time": 0.2756803035736084
    },
    "7": {
        "nf0": "edge_server_server_0",
        "nf1": "robot_sq1_fogNode_2",
        "nf2": "edge_server_server_0",
        "nf3": "robot_sq1_fogNode_2",
        "nf4": "edge_server_server_0",
        "nf5": "edge_server_server_0",
        "nf6": "robot_sq1_fogNode_2",
        "nf7": "edge_server_server_0",
        "nf8": "edge_server_server_0",
        "nf9": "edge_server_server_0",
        "nf10": "robot_sq1_fogNode_3",
        "nf11": "edge_server_server_0",
        "nf12": "edge_server_server_0",
        "nf13": "robot_sq1_fogNode_3",
        "nf14": "edge_server_server_0",
        "nf15": "edge_server_server_0",
        "nf16": "edge_server_server_0",
        "nf17": "edge_server_server_0",
        "nf18": "edge_server_server_0",
        "nf19": "robot_sq1_fogNode_2",
        "nf20": "edge_server_server_0",
        "nf21": "edge_server_server_0",
        "nf22": "edge_server_server_0",
        "nf23": "edge_server_server_0",
        "nf24": "edge_server_server_0",
        "nf25": "robot_sq1_fogNode_3",
        "worked": true,
        "Objective_value": 95.19021,
        "Running_time": 0.25592899322509766
    },
    "8": {
        "nf0": "edge_server_server_0",
        "nf1": "robot_sq1_fogNode_2",
        "nf2": "edge_server_server_0",
        "nf3": "robot_sq1_fogNode_2",
        "nf4": "edge_server_server_0",
        "nf5": "edge_server_server_0",
        "nf6": "robot_sq1_fogNode_2",
        "nf7": "edge_server_server_0",
        "nf8": "edge_server_server_0",
        "nf9": "edge_server_server_0",
        "nf10": "robot_sq1_fogNode_3",
        "nf11": "edge_server_server_0",
        "nf12": "edge_server_server_0",
        "nf13": "robot_sq1_fogNode_3",
        "nf14": "edge_server_server_0",
        "nf15": "edge_server_server_0",
        "nf16": "edge_server_server_0",
        "nf17": "edge_server_server_0",
        "nf18": "edge_server_server_0",
        "nf19": "robot_sq1_fogNode_2",
        "nf20": "edge_server_server_0",
        "nf21": "edge_server_server_0",
        "nf22": "edge_server_server_0",
        "nf23": "edge_server_server_0",
        "nf24": "edge_server_server_0",
        "nf25": "robot_sq1_fogNode_3",
        "worked": true,
        "Objective_value": 95.19021,
        "Running_time": 0.2618999481201172
    },
    "9": {
        "nf0": "edge_server_server_0",
        "nf1": "robot_sq1_fogNode_2",
        "nf2": "edge_server_server_0",
        "nf3": "robot_sq1_fogNode_2",
        "nf4": "edge_server_server_0",
        "nf5": "edge_server_server_0",
        "nf6": "robot_sq1_fogNode_2",
        "nf7": "edge_server_server_0",
        "nf8": "edge_server_server_0",
        "nf9": "edge_server_server_0",
        "nf10": "robot_sq1_fogNode_3",
        "nf11": "edge_server_server_0",
        "nf12": "edge_server_server_0",
        "nf13": "robot_sq1_fogNode_3",
        "nf14": "edge_server_server_0",
        "nf15": "edge_server_server_0",
        "nf16": "edge_server_server_0",
        "nf17": "edge_server_server_0",
        "nf18": "edge_server_server_0",
        "nf19": "robot_sq1_fogNode_2",
        "nf20": "edge_server_server_0",
        "nf21": "edge_server_server_0",
        "nf22": "edge_server_server_0",
        "nf23": "edge_server_server_0",
        "nf24": "edge_server_server_0",
        "nf25": "robot_sq1_fogNode_3",
        "worked": true,
        "Objective_value": 95.19021,
        "Running_time": 0.26313281059265137
    },
    "10": {
        "nf0": "edge_server_server_0",
        "nf1": "robot_sq1_fogNode_2",
        "nf2": "edge_server_server_0",
        "nf3": "robot_sq1_fogNode_2",
        "nf4": "edge_server_server_0",
        "nf5": "edge_server_server_0",
        "nf6": "robot_sq1_fogNode_2",
        "nf7": "edge_server_server_0",
        "nf8": "edge_server_server_0",
        "nf9": "edge_server_server_0",
        "nf10": "robot_sq1_fogNode_3",
        "nf11": "edge_server_server_0",
        "nf12": "edge_server_server_0",
        "nf13": "robot_sq1_fogNode_3",
        "nf14": "edge_server_server_0",
        "nf15": "edge_server_server_0",
        "nf16": "edge_server_server_0",
        "nf17": "edge_server_server_0",
        "nf18": "edge_server_server_0",
        "nf19": "robot_sq1_fogNode_2",
        "nf20": "edge_server_server_0",
        "nf21": "edge_server_server_0",
        "nf22": "edge_server_server_0",
        "nf23": "edge_server_server_0",
        "nf24": "edge_server_server_0",
        "nf25": "robot_sq1_fogNode_3",
        "worked": true,
        "Objective_value": 95.19021,
        "Running_time": 0.2623283863067627
    },
    "11": {
        "nf0": "edge_server_server_0",
        "nf1": "robot_sq1_fogNode_2",
        "nf2": "edge_server_server_0",
        "nf3": "robot_sq1_fogNode_2",
        "nf4": "edge_server_server_0",
        "nf5": "edge_server_server_0",
        "nf6": "robot_sq1_fogNode_2",
        "nf7": "edge_server_server_0",
        "nf8": "edge_server_server_0",
        "nf9": "edge_server_server_0",
        "nf10": "robot_sq1_fogNode_3",
        "nf11": "edge_server_server_0",
        "nf12": "edge_server_server_0",
        "nf13": "robot_sq1_fogNode_3",
        "nf14": "edge_server_server_0",
        "nf15": "edge_server_server_0",
        "nf16": "edge_server_server_0",
        "nf17": "edge_server_server_0",
        "nf18": "edge_server_server_0",
        "nf19": "robot_sq1_fogNode_2",
        "nf20": "edge_server_server_0",
        "nf21": "edge_server_server_0",
        "nf22": "edge_server_server_0",
        "nf23": "edge_server_server_0",
        "nf24": "edge_server_server_0",
        "nf25": "robot_sq1_fogNode_3",
        "worked": true,
        "Objective_value": 95.19021,
        "Running_time": 0.2610306739807129
    },
    "12": {
        "nf0": "edge_server_server_0",
        "nf1": "robot_sq1_fogNode_2",
        "nf2": "edge_server_server_0",
        "nf3": "robot_sq1_fogNode_2",
        "nf4": "edge_server_server_0",
        "nf5": "edge_server_server_0",
        "nf6": "robot_sq1_fogNode_2",
        "nf7": "edge_server_server_0",
        "nf8": "edge_server_server_0",
        "nf9": "edge_server_server_0",
        "nf10": "robot_sq1_fogNode_3",
        "nf11": "edge_server_server_0",
        "nf12": "edge_server_server_0",
        "nf13": "robot_sq1_fogNode_3",
        "nf14": "edge_server_server_0",
        "nf15": "edge_server_server_0",
        "nf16": "edge_server_server_0",
        "nf17": "edge_server_server_0",
        "nf18": "edge_server_server_0",
        "nf19": "robot_sq1_fogNode_2",
        "nf20": "edge_server_server_0",
        "nf21": "edge_server_server_0",
        "nf22": "edge_server_server_0",
        "nf23": "edge_server_server_0",
        "nf24": "edge_server_server_0",
        "nf25": "robot_sq1_fogNode_3",
        "worked": true,
        "Objective_value": 95.19021,
        "Running_time": 0.27519989013671875
    },
    "13": {
        "nf0": "edge_server_server_0",
        "nf1": "robot_sq1_fogNode_2",
        "nf2": "edge_server_server_0",
        "nf3": "robot_sq1_fogNode_2",
        "nf4": "edge_server_server_0",
        "nf5": "edge_server_server_0",
        "nf6": "robot_sq1_fogNode_2",
        "nf7": "edge_server_server_0",
        "nf8": "edge_server_server_0",
        "nf9": "edge_server_server_0",
        "nf10": "robot_sq1_fogNode_3",
        "nf11": "edge_server_server_0",
        "nf12": "edge_server_server_0",
        "nf13": "robot_sq1_fogNode_3",
        "nf14": "edge_server_server_0",
        "nf15": "edge_server_server_0",
        "nf16": "edge_server_server_0",
        "nf17": "edge_server_server_0",
        "nf18": "edge_server_server_0",
        "nf19": "robot_sq1_fogNode_2",
        "nf20": "edge_server_server_0",
        "nf21": "edge_server_server_0",
        "nf22": "edge_server_server_0",
        "nf23": "edge_server_server_0",
        "nf24": "edge_server_server_0",
        "nf25": "robot_sq1_fogNode_3",
        "worked": true,
        "Objective_value": 95.19021,
        "Running_time": 0.26839113235473633
    },
    "14": {
        "nf0": "edge_server_server_0",
        "nf1": "robot_sq1_fogNode_2",
        "nf2": "edge_server_server_0",
        "nf3": "robot_sq1_fogNode_2",
        "nf4": "edge_server_server_0",
        "nf5": "edge_server_server_0",
        "nf6": "robot_sq1_fogNode_2",
        "nf7": "edge_server_server_0",
        "nf8": "edge_server_server_0",
        "nf9": "edge_server_server_0",
        "nf10": "robot_sq1_fogNode_3",
        "nf11": "edge_server_server_0",
        "nf12": "edge_server_server_0",
        "nf13": "robot_sq1_fogNode_3",
        "nf14": "edge_server_server_0",
        "nf15": "edge_server_server_0",
        "nf16": "edge_server_server_0",
        "nf17": "edge_server_server_0",
        "nf18": "edge_server_server_0",
        "nf19": "robot_sq1_fogNode_2",
        "nf20": "edge_server_server_0",
        "nf21": "edge_server_server_0",
        "nf22": "edge_server_server_0",
        "nf23": "edge_server_server_0",
        "nf24": "edge_server_server_0",
        "nf25": "robot_sq1_fogNode_3",
        "worked": true,
        "Objective_value": 95.19021,
        "Running_time": 0.26819658279418945
    },
    "15": {
        "nf0": "edge_server_server_0",
        "nf1": "robot_sq1_fogNode_2",
        "nf2": "edge_server_server_0",
        "nf3": "robot_sq1_fogNode_2",
        "nf4": "edge_server_server_0",
        "nf5": "edge_server_server_0",
        "nf6": "robot_sq1_fogNode_2",
        "nf7": "edge_server_server_0",
        "nf8": "edge_server_server_0",
        "nf9": "edge_server_server_0",
        "nf10": "robot_sq1_fogNode_3",
        "nf11": "edge_server_server_0",
        "nf12": "edge_server_server_0",
        "nf13": "robot_sq1_fogNode_3",
        "nf14": "edge_server_server_0",
        "nf15": "edge_server_server_0",
        "nf16": "edge_server_server_0",
        "nf17": "edge_server_server_0",
        "nf18": "edge_server_server_0",
        "nf19": "robot_sq1_fogNode_2",
        "nf20": "edge_server_server_0",
        "nf21": "edge_server_server_0",
        "nf22": "edge_server_server_0",
        "nf23": "edge_server_server_0",
        "nf24": "edge_server_server_0",
        "nf25": "robot_sq1_fogNode_3",
        "worked": true,
        "Objective_value": 95.19021,
        "Running_time": 0.2687082290649414
    },
    "16": {
        "nf0": "edge_server_server_0",
        "nf1": "robot_sq1_fogNode_2",
        "nf2": "edge_server_server_0",
        "nf3": "robot_sq1_fogNode_2",
        "nf4": "edge_server_server_0",
        "nf5": "edge_server_server_0",
        "nf6": "robot_sq1_fogNode_2",
        "nf7": "edge_server_server_0",
        "nf8": "edge_server_server_0",
        "nf9": "edge_server_server_0",
        "nf10": "robot_sq1_fogNode_3",
        "nf11": "edge_server_server_0",
        "nf12": "edge_server_server_0",
        "nf13": "robot_sq1_fogNode_3",
        "nf14": "edge_server_server_0",
        "nf15": "edge_server_server_0",
        "nf16": "edge_server_server_0",
        "nf17": "edge_server_server_0",
        "nf18": "edge_server_server_0",
        "nf19": "robot_sq1_fogNode_2",
        "nf20": "edge_server_server_0",
        "nf21": "edge_server_server_0",
        "nf22": "edge_server_server_0",
        "nf23": "edge_server_server_0",
        "nf24": "edge_server_server_0",
        "nf25": "robot_sq1_fogNode_3",
        "worked": true,
        "Objective_value": 95.19021,
        "Running_time": 0.30945467948913574
    },
    "17": {
        "nf0": "edge_server_server_0",
        "nf1": "robot_sq1_fogNode_2",
        "nf2": "edge_server_server_0",
        "nf3": "robot_sq1_fogNode_2",
        "nf4": "edge_server_server_0",
        "nf5": "edge_server_server_0",
        "nf6": "robot_sq1_fogNode_2",
        "nf7": "edge_server_server_0",
        "nf8": "edge_server_server_0",
        "nf9": "edge_server_server_0",
        "nf10": "robot_sq1_fogNode_3",
        "nf11": "edge_server_server_0",
        "nf12": "edge_server_server_0",
        "nf13": "robot_sq1_fogNode_3",
        "nf14": "edge_server_server_0",
        "nf15": "edge_server_server_0",
        "nf16": "edge_server_server_0",
        "nf17": "edge_server_server_0",
        "nf18": "edge_server_server_0",
        "nf19": "robot_sq1_fogNode_2",
        "nf20": "edge_server_server_0",
        "nf21": "edge_server_server_0",
        "nf22": "edge_server_server_0",
        "nf23": "edge_server_server_0",
        "nf24": "edge_server_server_0",
        "nf25": "robot_sq1_fogNode_3",
        "worked": true,
        "Objective_value": 95.19021,
        "Running_time": 0.3087925910949707
    },
    "18": {
        "nf0": "edge_server_server_0",
        "nf1": "robot_sq1_fogNode_3",
        "nf2": "edge_server_server_0",
        "nf3": "robot_sq1_fogNode_3",
        "nf4": "edge_server_server_0",
        "nf5": "edge_server_server_0",
        "nf6": "robot_sq1_fogNode_3",
        "nf7": "edge_server_server_0",
        "nf8": "edge_server_server_0",
        "nf9": "edge_server_server_0",
        "nf10": "robot_sq1_fogNode_3",
        "nf11": "edge_server_server_0",
        "nf12": "edge_server_server_0",
        "nf13": "robot_sq1_fogNode_3",
        "nf14": "edge_server_server_0",
        "nf15": "edge_server_server_0",
        "nf16": "edge_server_server_0",
        "nf17": "edge_server_server_0",
        "nf18": "edge_server_server_0",
        "nf19": "edge_server_server_0",
        "nf20": "edge_server_server_0",
        "nf21": "edge_server_server_0",
        "nf22": "edge_server_server_0",
        "nf23": "edge_server_server_0",
        "nf24": "edge_server_server_0",
        "nf25": "robot_sq1_fogNode_3",
        "worked": true,
        "Objective_value": 88.13852999999999,
        "Running_time": 0.33173274993896484
    },
    "19": {
        "nf0": "edge_server_server_0",
        "nf1": "robot_sq1_fogNode_3",
        "nf2": "edge_server_server_0",
        "nf3": "robot_sq1_fogNode_3",
        "nf4": "edge_server_server_0",
        "nf5": "edge_server_server_0",
        "nf6": "robot_sq1_fogNode_3",
        "nf7": "edge_server_server_0",
        "nf8": "edge_server_server_0",
        "nf9": "edge_server_server_0",
        "nf10": "robot_sq1_fogNode_3",
        "nf11": "edge_server_server_0",
        "nf12": "edge_server_server_0",
        "nf13": "robot_sq1_fogNode_3",
        "nf14": "edge_server_server_0",
        "nf15": "edge_server_server_0",
        "nf16": "edge_server_server_0",
        "nf17": "edge_server_server_0",
        "nf18": "edge_server_server_0",
        "nf19": "edge_server_server_0",
        "nf20": "edge_server_server_0",
        "nf21": "edge_server_server_0",
        "nf22": "edge_server_server_0",
        "nf23": "edge_server_server_0",
        "nf24": "edge_server_server_0",
        "nf25": "robot_sq1_fogNode_3",
        "worked": true,
        "Objective_value": 88.13852999999999,
        "Running_time": 0.30846667289733887
    },
    "20": {
        "nf0": "edge_server_server_0",
        "nf1": "robot_sq1_fogNode_3",
        "nf2": "edge_server_server_0",
        "nf3": "robot_sq1_fogNode_3",
        "nf4": "edge_server_server_0",
        "nf5": "edge_server_server_0",
        "nf6": "robot_sq1_fogNode_3",
        "nf7": "edge_server_server_0",
        "nf8": "edge_server_server_0",
        "nf9": "edge_server_server_0",
        "nf10": "robot_sq1_fogNode_3",
        "nf11": "edge_server_server_0",
        "nf12": "edge_server_server_0",
        "nf13": "robot_sq1_fogNode_3",
        "nf14": "edge_server_server_0",
        "nf15": "edge_server_server_0",
        "nf16": "edge_server_server_0",
        "nf17": "edge_server_server_0",
        "nf18": "edge_server_server_0",
        "nf19": "edge_server_server_0",
        "nf20": "edge_server_server_0",
        "nf21": "edge_server_server_0",
        "nf22": "edge_server_server_0",
        "nf23": "edge_server_server_0",
        "nf24": "edge_server_server_0",
        "nf25": "robot_sq1_fogNode_3",
        "worked": true,
        "Objective_value": 88.13852999999999,
        "Running_time": 0.32944178581237793
    },
    "21": {
        "nf0": "edge_server_server_0",
        "nf1": "robot_sq1_fogNode_3",
        "nf2": "edge_server_server_0",
        "nf3": "robot_sq1_fogNode_3",
        "nf4": "edge_server_server_0",
        "nf5": "edge_server_server_0",
        "nf6": "robot_sq1_fogNode_3",
        "nf7": "edge_server_server_0",
        "nf8": "edge_server_server_0",
        "nf9": "edge_server_server_0",
        "nf10": "robot_sq1_fogNode_3",
        "nf11": "edge_server_server_0",
        "nf12": "edge_server_server_0",
        "nf13": "robot_sq1_fogNode_3",
        "nf14": "edge_server_server_0",
        "nf15": "edge_server_server_0",
        "nf16": "edge_server_server_0",
        "nf17": "edge_server_server_0",
        "nf18": "edge_server_server_0",
        "nf19": "edge_server_server_0",
        "nf20": "edge_server_server_0",
        "nf21": "edge_server_server_0",
        "nf22": "edge_server_server_0",
        "nf23": "edge_server_server_0",
        "nf24": "edge_server_server_0",
        "nf25": "robot_sq1_fogNode_3",
        "worked": true,
        "Objective_value": 88.13852999999999,
        "Running_time": 0.32851648330688477
    },
    "22": {
        "nf0": "edge_server_server_0",
        "nf1": "robot_sq1_fogNode_3",
        "nf2": "edge_server_server_0",
        "nf3": "robot_sq1_fogNode_3",
        "nf4": "edge_server_server_0",
        "nf5": "edge_server_server_0",
        "nf6": "robot_sq1_fogNode_3",
        "nf7": "edge_server_server_0",
        "nf8": "edge_server_server_0",
        "nf9": "edge_server_server_0",
        "nf10": "robot_sq1_fogNode_3",
        "nf11": "edge_server_server_0",
        "nf12": "edge_server_server_0",
        "nf13": "robot_sq1_fogNode_3",
        "nf14": "edge_server_server_0",
        "nf15": "edge_server_server_0",
        "nf16": "edge_server_server_0",
        "nf17": "edge_server_server_0",
        "nf18": "edge_server_server_0",
        "nf19": "edge_server_server_0",
        "nf20": "edge_server_server_0",
        "nf21": "edge_server_server_0",
        "nf22": "edge_server_server_0",
        "nf23": "edge_server_server_0",
        "nf24": "edge_server_server_0",
        "nf25": "robot_sq1_fogNode_3",
        "worked": true,
        "Objective_value": 88.13852999999999,
        "Running_time": 0.33071255683898926
    },
    "23": {
        "nf0": "edge_server_server_0",
        "nf1": "robot_sq1_fogNode_3",
        "nf2": "edge_server_server_0",
        "nf3": "robot_sq1_fogNode_3",
        "nf4": "edge_server_server_0",
        "nf5": "edge_server_server_0",
        "nf6": "robot_sq1_fogNode_3",
        "nf7": "edge_server_server_0",
        "nf8": "edge_server_server_0",
        "nf9": "edge_server_server_0",
        "nf10": "robot_sq1_fogNode_3",
        "nf11": "edge_server_server_0",
        "nf12": "edge_server_server_0",
        "nf13": "robot_sq1_fogNode_3",
        "nf14": "edge_server_server_0",
        "nf15": "edge_server_server_0",
        "nf16": "edge_server_server_0",
        "nf17": "edge_server_server_0",
        "nf18": "edge_server_server_0",
        "nf19": "edge_server_server_0",
        "nf20": "edge_server_server_0",
        "nf21": "edge_server_server_0",
        "nf22": "edge_server_server_0",
        "nf23": "edge_server_server_0",
        "nf24": "edge_server_server_0",
        "nf25": "robot_sq1_fogNode_3",
        "worked": true,
        "Objective_value": 88.13852999999999,
        "Running_time": 0.31168055534362793
    },
    "24": {
        "nf0": "edge_server_server_0",
        "nf1": "robot_sq1_fogNode_3",
        "nf2": "edge_server_server_0",
        "nf3": "robot_sq1_fogNode_3",
        "nf4": "edge_server_server_0",
        "nf5": "edge_server_server_0",
        "nf6": "robot_sq1_fogNode_3",
        "nf7": "edge_server_server_0",
        "nf8": "edge_server_server_0",
        "nf9": "edge_server_server_0",
        "nf10": "robot_sq1_fogNode_3",
        "nf11": "edge_server_server_0",
        "nf12": "edge_server_server_0",
        "nf13": "robot_sq1_fogNode_3",
        "nf14": "edge_server_server_0",
        "nf15": "edge_server_server_0",
        "nf16": "edge_server_server_0",
        "nf17": "edge_server_server_0",
        "nf18": "edge_server_server_0",
        "nf19": "edge_server_server_0",
        "nf20": "edge_server_server_0",
        "nf21": "edge_server_server_0",
        "nf22": "edge_server_server_0",
        "nf23": "edge_server_server_0",
        "nf24": "edge_server_server_0",
        "nf25": "robot_sq1_fogNode_3",
        "worked": true,
        "Objective_value": 88.13852999999999,
        "Running_time": 0.23730778694152832
    },
    "worked": true,
    "Running_time": 6.648782730102539,
    "Objective_value": 357.13347
}